pyRserve/__init__.py
pyRserve/misc.py
pyRserve/rconn.py
pyRserve/rexceptions.py
pyRserve/rparser.py
pyRserve/rserializer.py
pyRserve/rtypes.py
pyRserve/taggedContainers.py
pyRserve/version.txt
pyRserve-1.0.4.data/data/requirements.txt
pyRserve-1.0.4.data/data/requirements_dev.txt
pyRserve-1.0.4.dist-info/LICENSE
pyRserve-1.0.4.dist-info/METADATA
pyRserve-1.0.4.dist-info/WHEEL
pyRserve-1.0.4.dist-info/top_level.txt
pyRserve-1.0.4.dist-info/RECORD
