Metadata-Version: 2.1
Name: pyRserve
Version: 1.0.4
Summary: A Python client to remotely access the R statistic package via network
Home-page: https://github.com/ralhei/pyRserve
Author: Ralph Heinkel
Author-email: rh@ralph-heinkel.com
License: MIT license
Project-URL: Documentation, https://pyrserve.readthedocs.io/
Project-URL: Changelog, https://pyrserve.readthedocs.io/en/latest/changelog.html
Project-URL: PyPI, https://pypi.org/project/pyRserve/
Project-URL: Tracker, https://github.com/ralhei/pyRserve/issues
Keywords: R Rserve
Platform: unix
Platform: linux
Platform: cygwin
Platform: win32
Classifier: Development Status :: 5 - Production/Stable
Classifier: Environment :: Console
Classifier: License :: OSI Approved :: MIT License
Classifier: Operating System :: POSIX
Classifier: Operating System :: Microsoft :: Windows
Classifier: Programming Language :: Python
Classifier: Programming Language :: Python :: 2
Classifier: Programming Language :: Python :: 3
Classifier: Intended Audience :: Developers
Classifier: Topic :: Software Development :: Libraries
Classifier: Topic :: System :: Networking
Classifier: Topic :: Scientific/Engineering :: Information Analysis
Classifier: Topic :: Scientific/Engineering :: Mathematics
Requires-Python: >=2.7, !=3.0.*, !=3.1.*, !=3.2.*, !=3.3.*, !=3.4.*, !=3.5.*, <4
License-File: LICENSE
Requires-Dist: numpy<2
Provides-Extra: testing
Requires-Dist: pytest; extra == "testing"
Requires-Dist: flake8; extra == "testing"
Requires-Dist: coverage; extra == "testing"
Requires-Dist: sphinx; extra == "testing"
Requires-Dist: pre-commit; extra == "testing"
Requires-Dist: wheel; extra == "testing"
Requires-Dist: setuptools; extra == "testing"
Requires-Dist: twine; extra == "testing"
